sayou/visualizer/__init__.py
sayou/visualizer/pipeline.py
sayou/visualizer/core/exceptions.py
sayou/visualizer/core/schemas.py
sayou/visualizer/interfaces/base_renderer.py
sayou/visualizer/renderer/analytic_kg_renderer.py
sayou/visualizer/renderer/pyvis_renderer.py
sayou/visualizer/renderer/showcase_kg_renderer.py
sayou/visualizer/tracer/graph_tracer.py
sayou/visualizer/tracer/rich_tracer.py
sayou/visualizer/tracer/websocket_tracer.py
sayou_visualizer-0.0.11.dist-info/METADATA
sayou_visualizer-0.0.11.dist-info/WHEEL
sayou_visualizer-0.0.11.dist-info/RECORD
