Metadata-Version: 2.4
Name: sayou-visualizer
Version: 0.0.11
Summary: Visualizer components for the Sayou Data Platform
Project-URL: Homepage, https://www.sayouzone.com/
Project-URL: Documentation, https://sayouzone.github.io/sayou-fabric/
Project-URL: Repository, https://github.com/sayouzone/sayou-fabric
Author-email: Sayouzone <contact@sayouzone.com>
License:                                  Apache License
Classifier: License :: OSI Approved :: Apache Software License
Classifier: Operating System :: OS Independent
Classifier: Programming Language :: Python :: 3.9
Classifier: Programming Language :: Python :: 3.10
Classifier: Programming Language :: Python :: 3.11
Classifier: Topic :: Software Development :: Libraries :: Application Frameworks
Requires-Python: >=3.9
Requires-Dist: networkx==3.2.1
Requires-Dist: pyvis==0.3.2
Requires-Dist: rich==14.2.0
Requires-Dist: sayou-core~=0.3.0
Requires-Dist: websocket-client==1.9.0
